[
  {
    "name": "Wedding",
    "price": "47,043",
    "detail": "Khudad Pilaza Islamabad",
    "image": "./1/6.jpeg"
  },
  {
    "name": "Meeting",
    "price": "66,353",
    "detail": "Khudad Pilaza Lahore Punjab",
    "image": "./1/13.jpeg"
  },
  {
    "name": "Party",
    "price": "35,853",
    "detail": "Khudad Pilaza Karachi Sindh",
    "image": "./1/9.jpeg"
  },
  {
    "name": "Reception",
    "price": "47,043",
    "detail": "Khudad Pilaza Sukkur Sindh",
    "image": "./1/8.jpeg"
  }
]
